GAKTpore/__init__.py
GAKTpore/analysis.py
GAKTpore-1.1.2.dist-info/LICENSE
GAKTpore-1.1.2.dist-info/METADATA
GAKTpore-1.1.2.dist-info/WHEEL
GAKTpore-1.1.2.dist-info/top_level.txt
GAKTpore-1.1.2.dist-info/RECORD
