Metadata-Version: 2.1
Name: GAKTpore
Version: 1.1.2
Summary: A stereological analysis tool for porous materials
Home-page: https://github.com/gts4/GAKTpore
Author: Gareth Sheppard
Author-email: garethsheppard49@gmail.com
License: UNKNOWN
Project-URL: Bug Tracker, https://github.com/pypa/sampleproject/issues
Platform: UNKNOWN
Classifier: Programming Language :: Python :: 3
Classifier: License :: OSI Approved :: GNU General Public License v3 (GPLv3)
Classifier: Operating System :: OS Independent
Requires-Python: >=3
Requires-Dist: opencv-python
Requires-Dist: psutil
Requires-Dist: numpy
Requires-Dist: scipy
Requires-Dist: pyfftw
Requires-Dist: matplotlib
Requires-Dist: scikit-image
